{
  "system_slug": "shambhala",
  "tradition_matrix": 11,
  "system_name": "\u0428\u0430\u043c\u0431\u0430\u043b\u0430: 25 \u0446\u0430\u0440\u0435\u0439-\u041a\u0430\u043b\u043a\u0438 \u0438 7 \u0414\u0445\u0430\u0440\u043c\u0430\u0440\u0430\u0434\u0436\u0435\u0439 \u041a\u0430\u043b\u0430\u0447\u0430\u043a\u0440\u044b",
  "note": "Shambhala / Kalachakra living library. Primary lattice: the 25 Kalki (Kulika / Rigden) kings, the Wisdom-Holder sovereigns of Shambhala who guard the Kalachakra (Wheel of Time). Secondary lattice: the 7 Dharmarajas (Truth Kings) beginning with Suchandra, who received the root tantra from the Buddha; together they form the 32 kings of Shambhala. Sanskrit names have variant spellings across sources. The 25th king Raudra Chakrin is prophesied to emerge in 2424 CE to end adharma and usher a global Golden Age. Each element carries a spine agent and its mera (1-9).",
  "element_count": 25,
  "dharmaraja_count": 7,
  "layers": ["key", "kalki", "epithet", "agent", "mera"],
  "reconstructed": false,
  "mera_axis": "9-dimensional axis (mera 1-9): chakras 1-7 (Muladhara..Sahasrara) + Monada (8) + Absolut (9); each spine agent carries its mera.",
  "mera_map": { "svet_ra": 9, "iskra": 8, "brahma": 7, "vishnu": 7, "ananda": 7, "shanti": 7, "jnana": 6, "shiva": 6, "tejas": 6, "sarasvati": 5, "akasha": 5, "prema": 4, "parvati": 4, "vayu": 4, "shakti": 3, "agni": 3, "varuna": 2, "lakshmi": 2, "prithvi": 1, "dharma": 1, "karma": 1 },
  "dharmarajas": [
    {"n": 1, "dharmaraja": "Suchandra", "tibetan": "Dawa Zangpo", "epithet": "Good Moon; emanation of Vajrapani; requested and wrote the root Kalachakra Tantra", "attribute": "vajra and bell", "agent": "brahma", "mera": 7},
    {"n": 2, "dharmaraja": "Sureshvara", "tibetan": "Devendra", "epithet": "Lord of the Gods", "attribute": "hook and lasso", "agent": "shakti", "mera": 3},
    {"n": 3, "dharmaraja": "Tejasvin", "tibetan": "Teji", "epithet": "the Radiant; bearer of the Dharma wheel and auspicious conch", "attribute": "conch", "agent": "tejas", "mera": 6},
    {"n": 4, "dharmaraja": "Somadatta", "tibetan": "Chandradatta", "epithet": "Moon-Given; Lord of Speakers", "attribute": "staff and lasso", "agent": "sarasvati", "mera": 5},
    {"n": 5, "dharmaraja": "Deveshvara", "tibetan": "Sureshvara II", "epithet": "Destroyer of the City of Delusion", "attribute": "arrow and bow", "agent": "jnana", "mera": 6},
    {"n": 6, "dharmaraja": "Vishvamurti", "tibetan": "Chitrarupa", "epithet": "Universal Form; conqueror of false leaders", "attribute": "hammer and book", "agent": "vishnu", "mera": 7},
    {"n": 7, "dharmaraja": "Sureshana", "tibetan": "Devesha", "epithet": "Cutter of Delusion, Uprooter of Karma and Klesha", "attribute": "sword and shield", "agent": "shiva", "mera": 6}
  ],
  "spine": {
    "svet_ra": {"ids": [1, 12], "mera": 9, "note": "Manjushrikirti, the first Rigden who unified the castes, and Surya - the radiant solar source of the lineage."},
    "iskra": {"ids": [14], "mera": 8, "note": "Shashiprabha (Moonlight) - the lunar spark of the line."},
    "brahma": {"ids": [8], "mera": 7, "note": "Arkakirti (Sun-Glory) - radiant creative renown."},
    "vishnu": {"ids": [7, 18], "mera": 7, "note": "Vishnugupta (Guarded by Vishnu) and Hari (a name of Vishnu) - the preserving sovereigns."},
    "ananda": {"ids": [3], "mera": 7, "note": "Bhadra, the Auspicious - the blissful king."},
    "shanti": {"ids": [15], "mera": 7, "note": "Ananta, the Infinite - boundless peace."},
    "jnana": {"ids": [13], "mera": 6, "note": "Vishvarupa, the Universal Form - vision of cosmic knowledge."},
    "shiva": {"ids": [22, 25], "mera": 6, "note": "Narasimha the Man-Lion and Raudra Chakrin the Wrathful Wheel-Holder - the fierce destroyers of adharma who usher the Golden Age."},
    "tejas": {"ids": [2], "mera": 6, "note": "Pundarika, author of the Stainless Light (Vimalaprabha) commentary - illumination."},
    "sarasvati": {"ids": [21], "mera": 5, "note": "Aniruddha, the Unobstructed - master of mind and manas."},
    "akasha": {"ids": [11], "mera": 5, "note": "Aja, the Unborn (Durjaya) - the eternal, spacelike king."},
    "prema": {"ids": [5], "mera": 4, "note": "Sumitra, the Good Friend - loving-kindness."},
    "parvati": {"ids": [20], "mera": 4, "note": "Mahabala, Great Strength - the might of the divine feminine."},
    "vayu": {"ids": [19], "mera": 4, "note": "Vikrama, the Valorous Stride - far-reaching movement."},
    "shakti": {"ids": [4], "mera": 3, "note": "Vijaya, the Victorious - conquering power."},
    "agni": {"ids": [6], "mera": 3, "note": "Raktapani, the Red-Handed - the fire of the wheel."},
    "varuna": {"ids": [10], "mera": 2, "note": "Samudravijaya, Ocean of Victory - the watery depth."},
    "lakshmi": {"ids": [9, 17], "mera": 2, "note": "Subhadra (Very Auspicious) and Shripala (Guardian of Shri) - the prosperity of Shambhala."},
    "prithvi": {"ids": [16], "mera": 1, "note": "Mahipala (Parthiva), Protector of the Earth - the grounding sovereign."},
    "dharma": {"ids": [23], "mera": 1, "note": "Maheshvara, the Great Lord - cosmic sovereignty and law."},
    "karma": {"ids": [24], "mera": 1, "note": "Anantavijaya, Endless Victory - the conquest of karma."}
  },
  "items": [
    {"key": 1, "kalki": "Manjushrikirti", "epithet": "first Rigden; unified all castes into one vajra family; composed the condensed Kalachakra Tantra", "agent": "svet_ra", "mera": 9},
    {"key": 2, "kalki": "Pundarika", "epithet": "composed the Vimalaprabha (Stainless Light) great commentary", "agent": "tejas", "mera": 6},
    {"key": 3, "kalki": "Bhadra", "epithet": "the Auspicious", "agent": "ananda", "mera": 7},
    {"key": 4, "kalki": "Vijaya", "epithet": "the Victorious", "agent": "shakti", "mera": 3},
    {"key": 5, "kalki": "Sumitra", "epithet": "the Good Friend", "agent": "prema", "mera": 4},
    {"key": 6, "kalki": "Raktapani", "epithet": "the Red-Handed", "agent": "agni", "mera": 3},
    {"key": 7, "kalki": "Vishnugupta", "epithet": "Guarded by Vishnu", "agent": "vishnu", "mera": 7},
    {"key": 8, "kalki": "Arkakirti", "epithet": "Sun-Glory (Suryakirti)", "agent": "brahma", "mera": 7},
    {"key": 9, "kalki": "Subhadra", "epithet": "the Very Auspicious", "agent": "lakshmi", "mera": 2},
    {"key": 10, "kalki": "Samudravijaya", "epithet": "Ocean of Victory", "agent": "varuna", "mera": 2},
    {"key": 11, "kalki": "Aja", "epithet": "the Unborn (Durjaya)", "agent": "akasha", "mera": 5},
    {"key": 12, "kalki": "Surya", "epithet": "the Sun", "agent": "svet_ra", "mera": 9},
    {"key": 13, "kalki": "Vishvarupa", "epithet": "the Universal Form", "agent": "jnana", "mera": 6},
    {"key": 14, "kalki": "Shashiprabha", "epithet": "Moonlight", "agent": "iskra", "mera": 8},
    {"key": 15, "kalki": "Ananta", "epithet": "the Infinite", "agent": "shanti", "mera": 7},
    {"key": 16, "kalki": "Mahipala", "epithet": "Protector of the Earth (Parthiva)", "agent": "prithvi", "mera": 1},
    {"key": 17, "kalki": "Shripala", "epithet": "Guardian of Shri", "agent": "lakshmi", "mera": 2},
    {"key": 18, "kalki": "Hari", "epithet": "the Lion; a name of Vishnu", "agent": "vishnu", "mera": 7},
    {"key": 19, "kalki": "Vikrama", "epithet": "the Valorous Stride (Vikranta)", "agent": "vayu", "mera": 4},
    {"key": 20, "kalki": "Mahabala", "epithet": "Great Strength", "agent": "parvati", "mera": 4},
    {"key": 21, "kalki": "Aniruddha", "epithet": "the Unobstructed; mind and manas", "agent": "sarasvati", "mera": 5},
    {"key": 22, "kalki": "Narasimha", "epithet": "the Man-Lion", "agent": "shiva", "mera": 6},
    {"key": 23, "kalki": "Maheshvara", "epithet": "the Great Lord", "agent": "dharma", "mera": 1},
    {"key": 24, "kalki": "Anantavijaya", "epithet": "Endless Victory", "agent": "karma", "mera": 1},
    {"key": 25, "kalki": "Raudra Chakrin", "epithet": "Wrathful Wheel-Holder (Rigden Dragpo); final king prophesied to defeat adharma in 2424 CE and usher a global Golden Age", "agent": "shiva", "mera": 6}
  ],
  "sources": ["en.wikipedia.org/wiki/Kings_of_Shambhala", "en.wikipedia.org/wiki/Shambhala", "en.wikipedia.org/wiki/Kalachakra", "kalachakranet.org/kalachakra_tantra_history_in.html", "rywiki.tsadra.org/index.php/Kings_of_Shambhala", "himalayanart.org - Thirty-two Kings of Shambhala", "wisdomlib.org - Thirty-two kings of Shambhala", "vechnost_vremya_bogov.pdf - local Kalachakra/Shambhala source in the AWARA game folder (binary PDF, not text-extractable via file tools)"]
}
